powerschoolapi_cars1n/AccessToken.py
powerschoolapi_cars1n/BaseFunctions.py
powerschoolapi_cars1n/DataAccess.py
powerschoolapi_cars1n/__init__.py
powerschoolapi_cars1n-1.0.5.dist-info/METADATA
powerschoolapi_cars1n-1.0.5.dist-info/WHEEL
powerschoolapi_cars1n-1.0.5.dist-info/licenses/LICENSE
powerschoolapi_cars1n-1.0.5.dist-info/RECORD
