Metadata-Version: 2.3
Name: powerschoolapi_cars1n
Version: 1.0.5
Summary: A small package to interact with powerschool's api
Project-URL: Homepage, https://github.com/cars1n/powerschoolapi
Author-email: Carson Williams <14williamsc@gmail.com>
License: Copyright (c) 2018 The Python Packaging Authority
License-File: LICENSE
Keywords: api,powerschool,powerschoolapi,powerschoolapi_cars1n
Classifier: License :: OSI Approved :: MIT License
Classifier: Operating System :: OS Independent
Classifier: Programming Language :: Python :: 3
Requires-Python: >=3.8
Requires-Dist: icecream
Requires-Dist: python-dotenv
Requires-Dist: requests
Requires-Dist: urllib3
